mh.py
setup.py
mh_cli/__init__.py
mh_cli/common.py
mh_cli/gi.py
mh_cli/inbox.py
mh_cli/rec.py
mh_cli/series.py
mh_pages/__init__.py
mh_pages/pages/__init__.py
mh_pages/pages/locators.py
mh_pages/pages/page.py
mh_ui_testing.egg-info/PKG-INFO
mh_ui_testing.egg-info/SOURCES.txt
mh_ui_testing.egg-info/dependency_links.txt
mh_ui_testing.egg-info/entry_points.txt
mh_ui_testing.egg-info/requires.txt
mh_ui_testing.egg-info/top_level.txt