Metadata-Version: 1.0
Name: mh-ui-testing
Version: 0.9.0
Summary: Automated admin tasks and tests DCE Matterhorn
Home-page: https://github.com/harvard-dce/mh-ui-testing
Author: Jay Luker
Author-email: jay_luker@harvard.edu
License: Apache 2.0
Platform: UNKNOWN
